mplshared/__init__.py
mplshared/geometry.py
mplshared/slopes.py
mplshared/step.py
tests/__init__.py
tests/test_geometry.py
tests/test_slopes.py
tests/test_step.py
mplshared-0.1.2.dist-info/LICENSE
mplshared-0.1.2.dist-info/METADATA
mplshared-0.1.2.dist-info/WHEEL
mplshared-0.1.2.dist-info/top_level.txt
mplshared-0.1.2.dist-info/RECORD
