Metadata-Version: 2.1
Name: mplshared
Version: 0.1.2
Summary: Some tools for matplotlib
Home-page: https://github.com/maroba/mplshared
Author: Matthias Baer
Author-email: matthias.r.baer@googlemail.com
License: MIT
Platform: ALL
Classifier: Operating System :: OS Independent
Classifier: Programming Language :: Python :: 3
Requires-Python: >=3.6
License-File: LICENSE
Requires-Dist: sphinx
Requires-Dist: matplotlib
Requires-Dist: numpy
